mcp_dev_toolkit/__init__.py
mcp_dev_toolkit/cli.py
mcp_dev_toolkit/core.py
mcp_dev_toolkit/generators.py
mcp_dev_toolkit/middleware.py
mcp_dev_toolkit/schema.py
mcp_dev_toolkit-1.0.0.dist-info/METADATA
mcp_dev_toolkit-1.0.0.dist-info/WHEEL
mcp_dev_toolkit-1.0.0.dist-info/entry_points.txt
mcp_dev_toolkit-1.0.0.dist-info/licenses/LICENSE
mcp_dev_toolkit-1.0.0.dist-info/RECORD
