Metadata-Version: 2.4
Name: mcp-dev-toolkit
Version: 1.0.0
Summary: A comprehensive development toolkit for building Model Context Protocol (MCP) tools and servers
Project-URL: Homepage, https://github.com/mcp-toolkit/mcp-dev-toolkit
Project-URL: Documentation, https://github.com/mcp-toolkit/mcp-dev-toolkit#readme
Project-URL: Repository, https://github.com/mcp-toolkit/mcp-dev-toolkit
Project-URL: Issues, https://github.com/mcp-toolkit/mcp-dev-toolkit/issues
Project-URL: Changelog, https://github.com/mcp-toolkit/mcp-dev-toolkit/releases
Author-email: MCP Development Community <mcp-dev-toolkit@proton.me>
License-Expression: MIT
License-File: LICENSE
Keywords: ai-tools,development-toolkit,mcp,model-context-protocol,sdk,server-tools
Classifier: Development Status :: 5 - Production/Stable
Classifier: Intended Audience :: Developers
Classifier: License :: OSI Approved :: MIT License
Classifier: Operating System :: OS Independent
Classifier: Programming Language :: Python :: 3
Classifier: Programming Language :: Python :: 3.8
Classifier: Programming Language :: Python :: 3.9
Classifier: Programming Language :: Python :: 3.10
Classifier: Programming Language :: Python :: 3.11
Classifier: Programming Language :: Python :: 3.12
Classifier: Topic :: Internet :: WWW/HTTP :: HTTP Servers
Classifier: Topic :: Software Development :: Code Generators
Classifier: Topic :: Software Development :: Libraries :: Python Modules
Requires-Python: >=3.8
Requires-Dist: mcp>=1.0.0
Requires-Dist: pydantic>=2.0.0
Provides-Extra: dev
Requires-Dist: black>=23.0.0; extra == 'dev'
Requires-Dist: flake8>=6.0.0; extra == 'dev'
Requires-Dist: isort>=5.12.0; extra == 'dev'
Requires-Dist: mypy>=1.0.0; extra == 'dev'
Requires-Dist: pre-commit>=3.0.0; extra == 'dev'
Requires-Dist: pytest-asyncio>=0.21.0; extra == 'dev'
Requires-Dist: pytest>=7.0.0; extra == 'dev'
Provides-Extra: docs
Requires-Dist: myst-parser>=2.0.0; extra == 'docs'
Requires-Dist: sphinx-rtd-theme>=1.3.0; extra == 'docs'
Requires-Dist: sphinx>=6.0.0; extra == 'docs'
Provides-Extra: full
Requires-Dist: aiohttp>=3.8.0; extra == 'full'
Requires-Dist: jinja2>=3.0.0; extra == 'full'
Requires-Dist: pyyaml>=6.0; extra == 'full'
Provides-Extra: test
Requires-Dist: coverage>=7.0.0; extra == 'test'
Requires-Dist: pytest-asyncio>=0.21.0; extra == 'test'
Requires-Dist: pytest-cov>=4.0.0; extra == 'test'
Requires-Dist: pytest>=7.0.0; extra == 'test'
